minispec/__init__.py
minispec/_cache.py
minispec/filters.py
minispec/version.py
minispec/core/__init__.py
minispec/core/fft.py
minispec/core/spectrum.py
minispec/core/time_frequency.py
minispec/feature/__init__.py
minispec/feature/spectral.py
minispec/util/__init__.py
minispec/util/exceptions.py
minispec/util/utils.py
minispec/util/example_data/Kevin_MacLeod_-_Vibe_Ace.ogg
minispec-0.1.1.dist-info/LICENSE.md
minispec-0.1.1.dist-info/METADATA
minispec-0.1.1.dist-info/WHEEL
minispec-0.1.1.dist-info/top_level.txt
minispec-0.1.1.dist-info/RECORD
