Metadata-Version: 2.1
Name: minispec
Version: 0.1.1
Summary: Minimal module for computing audio spectrograms
Home-page: http://github.com/marl/minispec
Author: Jason Cramer, Ho-Hsiang Wu, Justin Salamon, and Mark Cartwright
Author-email: jtcramer@nyu.edu
License: ISC
Download-URL: http://github.com/marl/minispec/releases
Keywords: audio music sound
Platform: UNKNOWN
Classifier: License :: OSI Approved :: MIT License
Classifier: Programming Language :: Python
Classifier: Development Status :: 3 - Alpha
Classifier: Intended Audience :: Developers
Classifier: Topic :: Multimedia :: Sound/Audio :: Analysis
Classifier: Programming Language :: Python :: 2
Classifier: Programming Language :: Python :: 2.7
Classifier: Programming Language :: Python :: 3
Classifier: Programming Language :: Python :: 3.4
Classifier: Programming Language :: Python :: 3.5
Classifier: Programming Language :: Python :: 3.6
Classifier: Programming Language :: Python :: 3.7
Requires-Dist: numpy (>=1.8.0)
Requires-Dist: scipy (>=1.0.0)
Requires-Dist: joblib (>=0.12)
Requires-Dist: decorator (>=3.0.0)
Requires-Dist: six (>=1.3)
Provides-Extra: docs
Requires-Dist: numpydoc ; extra == 'docs'
Requires-Dist: sphinx (!=1.3.1) ; extra == 'docs'
Requires-Dist: sphinx-rtd-theme ; extra == 'docs'
Requires-Dist: sphinxcontrib-versioning (>=2.2.1) ; extra == 'docs'
Provides-Extra: tests
Requires-Dist: resampy (>=0.2.0) ; extra == 'tests'
Requires-Dist: audioread (>=2.0.0) ; extra == 'tests'
Requires-Dist: pytest-mpl ; extra == 'tests'
Requires-Dist: pytest-cov ; extra == 'tests'
Requires-Dist: pytest (<4) ; extra == 'tests'
